qy/__init__.py
qy/__main__.py
qy/_reader.py
qy/cli.py
qy/core.py
qy/operator.py
qy/operators/__init__.py
QyLang-0.0.4.dist-info/LICENSE
QyLang-0.0.4.dist-info/METADATA
QyLang-0.0.4.dist-info/WHEEL
QyLang-0.0.4.dist-info/entry_points.txt
QyLang-0.0.4.dist-info/top_level.txt
QyLang-0.0.4.dist-info/RECORD
