Metadata-Version: 2.1
Name: QyLang
Version: 0.0.4
Summary: Qy Lang, a Lisp language implemented in and based on Python
Home-page: https://github.com/Cosmic-Developers-Union/Qy
Author: Ge
Author-email: cosplox@outlook.com
License: Apache License 2.0
Classifier: Programming Language :: Python :: 3
Classifier: Programming Language :: Lisp
Classifier: License :: OSI Approved :: Apache Software License
Classifier: Operating System :: OS Independent
Requires-Python: >=3.8
License-File: LICENSE
Requires-Dist: lark>=1.2.2
